remlang/__init__.py
remlang/console.py
remlang/execute.py
remlang/intepreter.py
remlang/compiler/__init__.py
remlang/compiler/ast.py
remlang/compiler/control_flow.py
remlang/compiler/err.py
remlang/compiler/linked_list.py
remlang/compiler/module.py
remlang/compiler/msg.py
remlang/compiler/order_dual_opt.py
remlang/compiler/pattern_matching.py
remlang/compiler/reference_collections.py
remlang/compiler/rem_parser.py
remlang/compiler/test_lang.py
remlang/compiler/tk.py
remlang/compiler/utils.py
remlang/standard/__init__.py
remlang/standard/collections.py
remlang/standard/curry.py
remlang/standard/default.py
remlang/standard/io.py
remlang/standard/module.py
remlang/standard/path.py
remlang/standard/syntax.py
remlang-0.5.dist-info/DESCRIPTION.rst
remlang-0.5.dist-info/METADATA
remlang-0.5.dist-info/RECORD
remlang-0.5.dist-info/WHEEL
remlang-0.5.dist-info/entry_points.txt
remlang-0.5.dist-info/metadata.json
remlang-0.5.dist-info/top_level.txt
