Metadata-Version: 2.0
Name: remlang
Version: 0.5
Summary: rem langauge, which is very comfortable.
Home-page: https://github.com/thautwarm/Rem
Author: thautwarm
Author-email: twshere@outlook.com
License: MIT
Platform: any
Classifier: Programming Language :: Python :: 3.6
Classifier: Programming Language :: Python :: 3.7
Classifier: Programming Language :: Python :: Implementation :: CPython
Requires-Dist: toolz
Requires-Dist: EBNFParser (>=2.1.2)
